MANIFEST.in
README.rst
setup.py
xlserver/__init__.py
xlserver/index.html
xlserver/xlserver.py
xlserver.egg-info/PKG-INFO
xlserver.egg-info/SOURCES.txt
xlserver.egg-info/dependency_links.txt
xlserver.egg-info/entry_points.txt
xlserver.egg-info/requires.txt
xlserver.egg-info/top_level.txt
xlserver/.idea/HTTPServer.iml
xlserver/.idea/misc.xml
xlserver/.idea/modules.xml
xlserver/.idea/workspace.xml
xlserver/datatables/datatables.min.css
xlserver/datatables/datatables.min.js
xlserver/datatables/Bootstrap-3.3.6/fonts/glyphicons-halflings-regular.eot
xlserver/datatables/Bootstrap-3.3.6/fonts/glyphicons-halflings-regular.svg
xlserver/datatables/Bootstrap-3.3.6/fonts/glyphicons-halflings-regular.ttf
xlserver/datatables/Bootstrap-3.3.6/fonts/glyphicons-halflings-regular.woff
xlserver/datatables/Bootstrap-3.3.6/fonts/glyphicons-halflings-regular.woff2
xlserver/templates/index.template
xlserver/templates/index_error.template
xlserver/templates/table.template
xlserver/templates/table_row_col.template
xlserver/templates/table_row_col_head.template
xlserver/templates/table_rows.template
xlserver/templates/tabs.template